{
  "items": [
    {
      "str": "— 856 —",
      "dir": "ltr",
      "width": 43.05,
      "height": 10,
      "transform": [
        10,
        0,
        0,
        10,
        230.1274,
        32.0001
      ],
      "fontName": "g_d0_f3",
      "hasEOL": false
    },
    {
      "str": "Mandate for Leadership: The Conservative Promise",
      "dir": "ltr",
      "width": 230.1453,
      "height": 9,
      "transform": [
        9,
        0,
        0,
        9,
        136.9111,
        664.4
      ],
      "fontName": "g_d0_f12",
      "hasEOL": false
    },
    {
      "str": "",
      "dir": "ltr",
      "width": 0,
      "height": 0,
      "transform": [
        10.5,
        0,
        0,
        10.5,
        89.4264,
        631.9999
      ],
      "fontName": "g_d0_f4",
      "hasEOL": true
    },
    {
      "str": "Administration gave the green light for recipients to spend those funds to",
      "dir": "ltr",
      "width": 327.53700000000015,
      "height": 10.5,
      "transform": [
        10.5,
        0,
        0,
        10.5,
        89.4264,
        631.9999
      ],
      "fontName": "g_d0_f4",
      "hasEOL": false
    },
    {
      "str": "",
      "dir": "ltr",
      "width": 0,
      "height": 0,
      "transform": [
        10.5,
        0,
        0,
        10.5,
        90.36,
        617.9999
      ],
      "fontName": "g_d0_f4",
      "hasEOL": true
    },
    {
      "str": "overbuild existing high-speed networks in communities that already have",
      "dir": "ltr",
      "width": 328.7340000000001,
      "height": 10.5,
      "transform": [
        10.5,
        0,
        0,
        10.5,
        90.36,
        617.9999
      ],
      "fontName": "g_d0_f4",
      "hasEOL": false
    },
    {
      "str": "",
      "dir": "ltr",
      "width": 0,
      "height": 0,
      "transform": [
        10.5,
        0,
        0,
        10.5,
        90.2304,
        603.9999
      ],
      "fontName": "g_d0_f4",
      "hasEOL": true
    },
    {
      "str": "multiple broadband providers. A new Administration should eliminate",
      "dir": "ltr",
      "width": 316.08255000000014,
      "height": 10.5,
      "transform": [
        10.5,
        0,
        0,
        10.5,
        90.2304,
        603.9999
      ],
      "fontName": "g_d0_f4",
      "hasEOL": false
    },
    {
      "str": "",
      "dir": "ltr",
      "width": 0,
      "height": 0,
      "transform": [
        10.5,
        0,
        0,
        10.5,
        90.3564,
        589.9999
      ],
      "fontName": "g_d0_f4",
      "hasEOL": true
    },
    {
      "str": "government-funded overbuilding of existing networks.",
      "dir": "ltr",
      "width": 245.22855,
      "height": 10.5,
      "transform": [
        10.5,
        0,
        0,
        10.5,
        90.3564,
        589.9999
      ],
      "fontName": "g_d0_f4",
      "hasEOL": false
    },
    {
      "str": "",
      "dir": "ltr",
      "width": 0,
      "height": 0,
      "transform": [
        5,
        0,
        0,
        5,
        72.4752,
        563.4999
      ],
      "fontName": "g_d0_f13",
      "hasEOL": true
    },
    {
      "str": "l",
      "dir": "ltr",
      "width": 3.955,
      "height": 5,
      "transform": [
        5,
        0,
        0,
        5,
        72.4752,
        563.4999
      ],
      "fontName": "g_d0_f13",
      "hasEOL": false
    },
    {
      "str": " ",
      "dir": "ltr",
      "width": 2.6316399999999986,
      "height": 0,
      "transform": [
        5,
        0,
        0,
        5,
        76.4302,
        563.4999
      ],
      "fontName": "g_d0_f13",
      "hasEOL": false
    },
    {
      "str": "Adopt a national coordinating strategy.",
      "dir": "ltr",
      "width": 191.8770000000001,
      "height": 10.5,
      "transform": [
        10.5,
        0,
        0,
        10.5,
        89.5884,
        561.9999
      ],
      "fontName": "g_d0_f11",
      "hasEOL": false
    },
    {
      "str": " ",
      "dir": "ltr",
      "width": 0.18377142857143877,
      "height": 0,
      "transform": [
        10.5,
        0,
        0,
        10.5,
        281.46539999999993,
        561.9999
      ],
      "fontName": "g_d0_f11",
      "hasEOL": false
    },
    {
      "str": "Hundreds of billions of",
      "dir": "ltr",
      "width": 103.29900000000006,
      "height": 10.5,
      "transform": [
        10.5,
        0,
        0,
        10.5,
        283.39500000000004,
        561.9999
      ],
      "fontName": "g_d0_f4",
      "hasEOL": false
    },
    {
      "str": "",
      "dir": "ltr",
      "width": 0,
      "height": 0,
      "transform": [
        10.5,
        0,
        0,
        10.5,
        90.2304,
        547.9999
      ],
      "fontName": "g_d0_f4",
      "hasEOL": true
    },
    {
      "str": "infrastructure dollars have been appropriated by Congress or budgeted by",
      "dir": "ltr",
      "width": 330.2974500000001,
      "height": 10.5,
      "transform": [
        10.5,
        0,
        0,
        10.5,
        90.2304,
        547.9999
      ],
      "fontName": "g_d0_f4",
      "hasEOL": false
    },
    {
      "str": "",
      "dir": "ltr",
      "width": 0,
      "height": 0,
      "transform": [
        10.5,
        0,
        0,
        10.5,
        90.318,
        533.9999
      ],
      "fontName": "g_d0_f4",
      "hasEOL": true
    },
    {
      "str": "agencies over the past couple of years that can be used to end the digital",
      "dir": "ltr",
      "width": 318.74850000000015,
      "height": 10.5,
      "transform": [
        10.5,
        0,
        0,
        10.5,
        90.318,
        533.9999
      ],
      "fontName": "g_d0_f4",
      "hasEOL": false
    },
    {
      "str": "",
      "dir": "ltr",
      "width": 0,
      "height": 0,
      "transform": [
        10.5,
        0,
        0,
        10.5,
        90.36,
        519.9999
      ],
      "fontName": "g_d0_f4",
      "hasEOL": true
    },
    {
      "str": "divide. Yet, according to the U.S. Government Accountability Office, “U.S.",
      "dir": "ltr",
      "width": 324.90990000000016,
      "height": 10.5,
      "transform": [
        10.5,
        0,
        0,
        10.5,
        90.36,
        519.9999
      ],
      "fontName": "g_d0_f4",
      "hasEOL": false
    },
    {
      "str": "",
      "dir": "ltr",
      "width": 0,
      "height": 0,
      "transform": [
        10.5,
        0,
        0,
        10.5,
        90.4548,
        505.9999
      ],
      "fontName": "g_d0_f4",
      "hasEOL": true
    },
    {
      "str": "broadband efforts are not guided by a national strategy”; instead, “[f ]ederal",
      "dir": "ltr",
      "width": 335.5695000000001,
      "height": 10.5,
      "transform": [
        10.5,
        0,
        0,
        10.5,
        90.4548,
        505.9999
      ],
      "fontName": "g_d0_f4",
      "hasEOL": false
    },
    {
      "str": "",
      "dir": "ltr",
      "width": 0,
      "height": 0,
      "transform": [
        10.5,
        0,
        0,
        10.5,
        90.4548,
        491.9999
      ],
      "fontName": "g_d0_f4",
      "hasEOL": true
    },
    {
      "str": "broadband efforts are fragmented and overlapping, with more than 100",
      "dir": "ltr",
      "width": 317.4990000000001,
      "height": 10.5,
      "transform": [
        10.5,
        0,
        0,
        10.5,
        90.4548,
        491.9999
      ],
      "fontName": "g_d0_f4",
      "hasEOL": false
    },
    {
      "str": "",
      "dir": "ltr",
      "width": 0,
      "height": 0,
      "transform": [
        10.5,
        0,
        0,
        10.5,
        90.3984,
        477.9999
      ],
      "fontName": "g_d0_f4",
      "hasEOL": true
    },
    {
      "str": "programs administered by 15 agencies,” risking overbuilding as well",
      "dir": "ltr",
      "width": 301.8309000000001,
      "height": 10.5,
      "transform": [
        10.5,
        0,
        0,
        10.5,
        90.3984,
        477.9999
      ],
      "fontName": "g_d0_f4",
      "hasEOL": false
    },
    {
      "str": "",
      "dir": "ltr",
      "width": 0,
      "height": 0,
      "transform": [
        10.5,
        0,
        0,
        10.5,
        90.318,
        463.9999
      ],
      "fontName": "g_d0_f4",
      "hasEOL": true
    },
    {
      "str": "as wasteful duplication.",
      "dir": "ltr",
      "width": 105.777,
      "height": 10.5,
      "transform": [
        10.5,
        0,
        0,
        10.5,
        90.318,
        463.9999
      ],
      "fontName": "g_d0_f4",
      "hasEOL": false
    },
    {
      "str": "26",
      "dir": "ltr",
      "width": 6.6418275,
      "height": 6.1215,
      "transform": [
        6.1215,
        0,
        0,
        6.1215,
        196.0931,
        467.4964
      ],
      "fontName": "g_d0_f4",
      "hasEOL": false
    },
    {
      "str": " ",
      "dir": "ltr",
      "width": 0.31558809115412845,
      "height": 0,
      "transform": [
        6.1215,
        0,
        0,
        6.1215,
        202.7349275,
        467.4964
      ],
      "fontName": "g_d0_f4",
      "hasEOL": false
    },
    {
      "str": "Many of these programs remain plagued by",
      "dir": "ltr",
      "width": 193.12650000000002,
      "height": 10.5,
      "transform": [
        10.5,
        0,
        0,
        10.5,
        204.6668,
        463.9999
      ],
      "fontName": "g_d0_f4",
      "hasEOL": false
    },
    {
      "str": "",
      "dir": "ltr",
      "width": 0,
      "height": 0,
      "transform": [
        10.5,
        0,
        0,
        10.5,
        90.2304,
        449.9999
      ],
      "fontName": "g_d0_f4",
      "hasEOL": true
    },
    {
      "str": "inefficiency, further contributing to waste of limited taxpayer dollars.",
      "dir": "ltr",
      "width": 309.17145000000005,
      "height": 10.5,
      "transform": [
        10.5,
        0,
        0,
        10.5,
        90.2304,
        449.9999
      ],
      "fontName": "g_d0_f4",
      "hasEOL": false
    },
    {
      "str": "",
      "dir": "ltr",
      "width": 0,
      "height": 0,
      "transform": [
        10.5,
        0,
        0,
        10.5,
        89.9316,
        421.9999
      ],
      "fontName": "g_d0_f4",
      "hasEOL": true
    },
    {
      "str": "Moreover, the federal government is failing to put appropriate guardrails",
      "dir": "ltr",
      "width": 325.82550000000003,
      "height": 10.5,
      "transform": [
        10.5,
        0,
        0,
        10.5,
        89.9316,
        421.9999
      ],
      "fontName": "g_d0_f4",
      "hasEOL": false
    },
    {
      "str": "",
      "dir": "ltr",
      "width": 0,
      "height": 0,
      "transform": [
        10.5,
        0,
        0,
        10.5,
        90.2304,
        407.9999
      ],
      "fontName": "g_d0_f4",
      "hasEOL": true
    },
    {
      "str": "in place to govern the expenditure of billions in broadband funds. This",
      "dir": "ltr",
      "width": 313.71900000000016,
      "height": 10.5,
      "transform": [
        10.5,
        0,
        0,
        10.5,
        90.2304,
        407.9999
      ],
      "fontName": "g_d0_f4",
      "hasEOL": false
    },
    {
      "str": "",
      "dir": "ltr",
      "width": 0,
      "height": 0,
      "transform": [
        10.5,
        0,
        0,
        10.5,
        90.2304,
        393.9999
      ],
      "fontName": "g_d0_f4",
      "hasEOL": true
    },
    {
      "str": "is the regulatory equivalent of turning the spigot on full blast and then",
      "dir": "ltr",
      "width": 312.9304500000001,
      "height": 10.5,
      "transform": [
        10.5,
        0,
        0,
        10.5,
        90.2304,
        393.9999
      ],
      "fontName": "g_d0_f4",
      "hasEOL": false
    },
    {
      "str": "",
      "dir": "ltr",
      "width": 0,
      "height": 0,
      "transform": [
        10.5,
        0,
        0,
        10.5,
        90.096,
        379.9999
      ],
      "fontName": "g_d0_f4",
      "hasEOL": true
    },
    {
      "str": "walking away from the hose. There is a worrisome lack of adequate",
      "dir": "ltr",
      "width": 297.2329500000001,
      "height": 10.5,
      "transform": [
        10.5,
        0,
        0,
        10.5,
        90.096,
        379.9999
      ],
      "fontName": "g_d0_f4",
      "hasEOL": false
    },
    {
      "str": "",
      "dir": "ltr",
      "width": 0,
      "height": 0,
      "transform": [
        10.5,
        0,
        0,
        10.5,
        90.2868,
        365.9999
      ],
      "fontName": "g_d0_f4",
      "hasEOL": true
    },
    {
      "str": "tracking, measurement, and accountability standards governing all of this",
      "dir": "ltr",
      "width": 329.4994500000001,
      "height": 10.5,
      "transform": [
        10.5,
        0,
        0,
        10.5,
        90.2868,
        365.9999
      ],
      "fontName": "g_d0_f4",
      "hasEOL": false
    },
    {
      "str": "",
      "dir": "ltr",
      "width": 0,
      "height": 0,
      "transform": [
        10.5,
        0,
        0,
        10.5,
        90.4548,
        351.9999
      ],
      "fontName": "g_d0_f4",
      "hasEOL": true
    },
    {
      "str": "broadband spending. As a result, we are likely to see headline levels of waste,",
      "dir": "ltr",
      "width": 340.8300000000001,
      "height": 10.5,
      "transform": [
        10.5,
        0,
        0,
        10.5,
        90.4548,
        351.9999
      ],
      "fontName": "g_d0_f4",
      "hasEOL": false
    },
    {
      "str": "",
      "dir": "ltr",
      "width": 0,
      "height": 0,
      "transform": [
        10.5,
        0,
        0,
        10.5,
        90.4296,
        337.9999
      ],
      "fontName": "g_d0_f4",
      "hasEOL": true
    },
    {
      "str": "fraud, and abuse.",
      "dir": "ltr",
      "width": 76.15649999999998,
      "height": 10.5,
      "transform": [
        10.5,
        0,
        0,
        10.5,
        90.4296,
        337.9999
      ],
      "fontName": "g_d0_f4",
      "hasEOL": false
    },
    {
      "str": "",
      "dir": "ltr",
      "width": 0,
      "height": 0,
      "transform": [
        10.5,
        0,
        0,
        10.5,
        89.4264,
        309.9999
      ],
      "fontName": "g_d0_f4",
      "hasEOL": true
    },
    {
      "str": "A new Administration needs to bring fresh oversight to this spending and",
      "dir": "ltr",
      "width": 326.8965000000002,
      "height": 10.5,
      "transform": [
        10.5,
        0,
        0,
        10.5,
        89.4264,
        309.9999
      ],
      "fontName": "g_d0_f4",
      "hasEOL": false
    },
    {
      "str": "",
      "dir": "ltr",
      "width": 0,
      "height": 0,
      "transform": [
        10.5,
        0,
        0,
        10.5,
        90.3984,
        295.9999
      ],
      "fontName": "g_d0_f4",
      "hasEOL": true
    },
    {
      "str": "put a national strategy in place to ensure that the federal government adopts",
      "dir": "ltr",
      "width": 341.1754500000001,
      "height": 10.5,
      "transform": [
        10.5,
        0,
        0,
        10.5,
        90.3984,
        295.9999
      ],
      "fontName": "g_d0_f4",
      "hasEOL": false
    },
    {
      "str": "",
      "dir": "ltr",
      "width": 0,
      "height": 0,
      "transform": [
        10.5,
        0,
        0,
        10.5,
        90.318,
        281.9999
      ],
      "fontName": "g_d0_f4",
      "hasEOL": true
    },
    {
      "str": "a coordinated approach to its various broadband initiatives. Similarly, the",
      "dir": "ltr",
      "width": 328.16700000000003,
      "height": 10.5,
      "transform": [
        10.5,
        0,
        0,
        10.5,
        90.318,
        281.9999
      ],
      "fontName": "g_d0_f4",
      "hasEOL": false
    },
    {
      "str": "",
      "dir": "ltr",
      "width": 0,
      "height": 0,
      "transform": [
        10.5,
        0,
        0,
        10.5,
        90.2304,
        267.9999
      ],
      "fontName": "g_d0_f4",
      "hasEOL": true
    },
    {
      "str": "next Administration should ask the FCC to launch a review of its existing",
      "dir": "ltr",
      "width": 325.56195000000014,
      "height": 10.5,
      "transform": [
        10.5,
        0,
        0,
        10.5,
        90.2304,
        267.9999
      ],
      "fontName": "g_d0_f4",
      "hasEOL": false
    },
    {
      "str": "",
      "dir": "ltr",
      "width": 0,
      "height": 0,
      "transform": [
        10.5,
        0,
        0,
        10.5,
        90.4548,
        253.9999
      ],
      "fontName": "g_d0_f4",
      "hasEOL": true
    },
    {
      "str": "broadband programs, including the different components of the USF, with",
      "dir": "ltr",
      "width": 330.5505000000001,
      "height": 10.5,
      "transform": [
        10.5,
        0,
        0,
        10.5,
        90.4548,
        253.9999
      ],
      "fontName": "g_d0_f4",
      "hasEOL": false
    },
    {
      "str": "",
      "dir": "ltr",
      "width": 0,
      "height": 0,
      "transform": [
        10.5,
        0,
        0,
        10.5,
        90.2868,
        239.9999
      ],
      "fontName": "g_d0_f4",
      "hasEOL": true
    },
    {
      "str": "the goal of avoiding duplication, improving efficiency of existing programs,",
      "dir": "ltr",
      "width": 333.1009500000001,
      "height": 10.5,
      "transform": [
        10.5,
        0,
        0,
        10.5,
        90.2868,
        239.9999
      ],
      "fontName": "g_d0_f4",
      "hasEOL": false
    },
    {
      "str": "",
      "dir": "ltr",
      "width": 0,
      "height": 0,
      "transform": [
        10.5,
        0,
        0,
        10.5,
        90.318,
        225.9999
      ],
      "fontName": "g_d0_f4",
      "hasEOL": true
    },
    {
      "str": "and saving taxpayer money.",
      "dir": "ltr",
      "width": 123.41700000000002,
      "height": 10.5,
      "transform": [
        10.5,
        0,
        0,
        10.5,
        90.318,
        225.9999
      ],
      "fontName": "g_d0_f4",
      "hasEOL": false
    },
    {
      "str": "",
      "dir": "ltr",
      "width": 0,
      "height": 0,
      "transform": [
        5,
        0,
        0,
        5,
        73.2689,
        199.4999
      ],
      "fontName": "g_d0_f13",
      "hasEOL": true
    },
    {
      "str": "l",
      "dir": "ltr",
      "width": 3.955,
      "height": 5,
      "transform": [
        5,
        0,
        0,
        5,
        73.2689,
        199.4999
      ],
      "fontName": "g_d0_f13",
      "hasEOL": false
    },
    {
      "str": " ",
      "dir": "ltr",
      "width": 2.5833,
      "height": 0,
      "transform": [
        5,
        0,
        0,
        5,
        77.2239,
        199.4999
      ],
      "fontName": "g_d0_f13",
      "hasEOL": false
    },
    {
      "str": "Correct the FCC’s regulatory trajectory and encourage competition",
      "dir": "ltr",
      "width": 329.71889999999996,
      "height": 10.5,
      "transform": [
        10.5,
        0,
        0,
        10.5,
        90.1404,
        197.9999
      ],
      "fontName": "g_d0_f11",
      "hasEOL": false
    },
    {
      "str": "",
      "dir": "ltr",
      "width": 0,
      "height": 0,
      "transform": [
        10.5,
        0,
        0,
        10.5,
        90.4128,
        183.9999
      ],
      "fontName": "g_d0_f11",
      "hasEOL": true
    },
    {
      "str": "to improve connectivity.",
      "dir": "ltr",
      "width": 119.58450000000003,
      "height": 10.5,
      "transform": [
        10.5,
        0,
        0,
        10.5,
        90.4128,
        183.9999
      ],
      "fontName": "g_d0_f11",
      "hasEOL": false
    },
    {
      "str": " ",
      "dir": "ltr",
      "width": 0.18388571428570935,
      "height": 0,
      "transform": [
        10.5,
        0,
        0,
        10.5,
        209.99730000000005,
        183.9999
      ],
      "fontName": "g_d0_f11",
      "hasEOL": false
    },
    {
      "str": "The FCC is a New Deal–era agency. Its history",
      "dir": "ltr",
      "width": 205.66245000000015,
      "height": 10.5,
      "transform": [
        10.5,
        0,
        0,
        10.5,
        211.9281,
        183.9999
      ],
      "fontName": "g_d0_f4",
      "hasEOL": false
    },
    {
      "str": "",
      "dir": "ltr",
      "width": 0,
      "height": 0,
      "transform": [
        10.5,
        0,
        0,
        10.5,
        90.36,
        169.9999
      ],
      "fontName": "g_d0_f4",
      "hasEOL": true
    },
    {
      "str": "of regulation tends to reflect the view that the federal government should",
      "dir": "ltr",
      "width": 327.0214500000001,
      "height": 10.5,
      "transform": [
        10.5,
        0,
        0,
        10.5,
        90.36,
        169.9999
      ],
      "fontName": "g_d0_f4",
      "hasEOL": false
    },
    {
      "str": "",
      "dir": "ltr",
      "width": 0,
      "height": 0,
      "transform": [
        10.5,
        0,
        0,
        10.5,
        90.2304,
        155.9999
      ],
      "fontName": "g_d0_f4",
      "hasEOL": true
    },
    {
      "str": "impose heavy-handed regulation rather than relying on competition",
      "dir": "ltr",
      "width": 305.319,
      "height": 10.5,
      "transform": [
        10.5,
        0,
        0,
        10.5,
        90.2304,
        155.9999
      ],
      "fontName": "g_d0_f4",
      "hasEOL": false
    },
    {
      "str": "",
      "dir": "ltr",
      "width": 0,
      "height": 0,
      "transform": [
        10.5,
        0,
        0,
        10.5,
        90.318,
        141.9999
      ],
      "fontName": "g_d0_f4",
      "hasEOL": true
    },
    {
      "str": "and market forces to produce optimal outcomes. President Franklin D.",
      "dir": "ltr",
      "width": 314.6734500000002,
      "height": 10.5,
      "transform": [
        10.5,
        0,
        0,
        10.5,
        90.318,
        141.9999
      ],
      "fontName": "g_d0_f4",
      "hasEOL": false
    },
    {
      "str": "",
      "dir": "ltr",
      "width": 0,
      "height": 0,
      "transform": [
        10.5,
        0,
        0,
        10.5,
        89.9316,
        127.9999
      ],
      "fontName": "g_d0_f4",
      "hasEOL": true
    },
    {
      "str": "Roosevelt recommended that Congress create the FCC in February 1934",
      "dir": "ltr",
      "width": 323.2729500000002,
      "height": 10.5,
      "transform": [
        10.5,
        0,
        0,
        10.5,
        89.9316,
        127.9999
      ],
      "fontName": "g_d0_f4",
      "hasEOL": false
    },
    {
      "str": "",
      "dir": "ltr",
      "width": 0,
      "height": 0,
      "transform": [
        10.5,
        0,
        0,
        10.5,
        90.4296,
        113.9999
      ],
      "fontName": "g_d0_f4",
      "hasEOL": true
    },
    {
      "str": "for the purposes of establishing “a single Government agency charged",
      "dir": "ltr",
      "width": 311.2410000000001,
      "height": 10.5,
      "transform": [
        10.5,
        0,
        0,
        10.5,
        90.4296,
        113.9999
      ],
      "fontName": "g_d0_f4",
      "hasEOL": false
    },
    {
      "str": "",
      "dir": "ltr",
      "width": 0,
      "height": 0,
      "transform": [
        10.5,
        0,
        0,
        10.5,
        90.096,
        99.9999
      ],
      "fontName": "g_d0_f4",
      "hasEOL": true
    },
    {
      "str": "with broad authority” over the field of communications.",
      "dir": "ltr",
      "width": 249.69944999999998,
      "height": 10.5,
      "transform": [
        10.5,
        0,
        0,
        10.5,
        90.096,
        99.9999
      ],
      "fontName": "g_d0_f4",
      "hasEOL": false
    },
    {
      "str": "27",
      "dir": "ltr",
      "width": 6.4214535,
      "height": 6.1215,
      "transform": [
        6.1215,
        0,
        0,
        6.1215,
        339.7916,
        103.4964
      ],
      "fontName": "g_d0_f4",
      "hasEOL": false
    },
    {
      "str": " ",
      "dir": "ltr",
      "width": 0.31561651555990455,
      "height": 0,
      "transform": [
        6.1215,
        0,
        0,
        6.1215,
        346.21305350000006,
        103.4964
      ],
      "fontName": "g_d0_f4",
      "hasEOL": false
    },
    {
      "str": "Congress",
      "dir": "ltr",
      "width": 41.884499999999996,
      "height": 10.5,
      "transform": [
        10.5,
        0,
        0,
        10.5,
        348.1451,
        99.9999
      ],
      "fontName": "g_d0_f4",
      "hasEOL": false
    },
    {
      "str": "",
      "dir": "ltr",
      "width": 0,
      "height": 0,
      "transform": [
        10.5,
        0,
        0,
        10.5,
        90.3936,
        85.9999
      ],
      "fontName": "g_d0_f4",
      "hasEOL": true
    },
    {
      "str": "subsequently established the FCC through the Communications Act of 1934.",
      "dir": "ltr",
      "width": 342.1530000000002,
      "height": 10.5,
      "transform": [
        10.5,
        0,
        0,
        10.5,
        90.3936,
        85.9999
      ],
      "fontName": "g_d0_f4",
      "hasEOL": false
    },
    {
      "str": "",
      "dir": "ltr",
      "width": 0,
      "height": 0,
      "transform": [
        10.5,
        0,
        0,
        10.5,
        90.0348,
        71.9999
      ],
      "fontName": "g_d0_f4",
      "hasEOL": true
    },
    {
      "str": "Congress has passed a number of additional statutes—some broad, some",
      "dir": "ltr",
      "width": 322.6429500000002,
      "height": 10.5,
      "transform": [
        10.5,
        0,
        0,
        10.5,
        90.0348,
        71.9999
      ],
      "fontName": "g_d0_f4",
      "hasEOL": false
    }
  ],
  "styles": {
    "g_d0_f3": {
      "fontFamily": "sans-serif",
      "ascent": 1.008,
      "descent": -0.275,
      "vertical": false
    },
    "g_d0_f12": {
      "fontFamily": "sans-serif",
      "ascent": 1.008,
      "descent": -0.275,
      "vertical": false
    },
    "g_d0_f4": {
      "fontFamily": "serif",
      "ascent": 1.089,
      "descent": -0.312,
      "vertical": false
    },
    "g_d0_f13": {
      "fontFamily": "monospace",
      "ascent": 0.851,
      "descent": -0.148,
      "vertical": false
    },
    "g_d0_f11": {
      "fontFamily": "serif",
      "ascent": 1.143,
      "descent": -0.351,
      "vertical": false
    }
  },
  "lang": "en-US"
}